Metadata-Version: 2.1
Name: typetype
Version: 1.2.1
Summary: A command line typing game
Home-page: https://github.com/ahmet8zer/typetype
Author: Ahmet Ozer
